{"Alien": [227.8], "Amidar": [5.8], "Assault": [222.4], "Asterix": [210.0], "BankHeist": [14.2], "BattleZone": [2360.0], "Boxing": [0.1], "Breakout": [1.7], "ChopperCommand": [811.0], "CrazyClimber": [10780.5], "DemonAttack": [152.1], "Freeway": [0.0], "Frostbite": [65.2], "Gopher": [257.6], "Hero": [1027.0], "Jamesbond": [29.0], "Kangaroo": [52.0], "Krull": [1598.0], "KungFuMaster": [258.5], "MsPacman": [307.3], "Pong": [-20.7], "PrivateEye": [24.9], "Qbert": [163.9], "RoadRunner": [11.5], "Seaquest": [68.4], "UpNDown": [533.4]}
